pysmtester/__init__.py
pysmtester/cmdboottryconnect.py
pysmtester/cmdchipprogram.py
pysmtester/cmddirlist.py
pysmtester/cmdelectricaltestreadmeasurement.py
pysmtester/cmdelectricaltestsetupexternalmux.py
pysmtester/cmdelectricaltestsetuppair.py
pysmtester/cmdgetconfig.py
pysmtester/cmdmkdir.py
pysmtester/cmdreadchecksum.py
pysmtester/cmdreadfile.py
pysmtester/cmdrelayantenna.py
pysmtester/cmdremoveformat.py
pysmtester/cmdresetsmtester.py
pysmtester/cmdresettarget.py
pysmtester/cmdsetconfigdevicekeys.py
pysmtester/cmdsettargetpower.py
pysmtester/cmdtargetconnectionsetup.py
pysmtester/cmdtargetreadmeasurement.py
pysmtester/cmdtargetreadsense.py
pysmtester/cmduartbridge.py
pysmtester/cmdwritefile.py
pysmtester/globalvar.py
pysmtester/hexdef.py
pysmtester/smtesterasynchandler.py
pysmtester/smtesterdef.py
pysmtester/smtesterinit.py
pysmtester/spv1smtester_glibc.so
pysmtester/spv1smtester_win.dll
spv1/__init__.py
spv1/checkpathmodule.py
spv1/commandbasespv1.py
spv1/serialcommspv1.py
spv1/spsc.py
spv1/spv1.py
spv1/spv1dll.py
spv1/test.py
pysmtester-1.0.15.dist-info/LICENSE.txt
pysmtester-1.0.15.dist-info/METADATA
pysmtester-1.0.15.dist-info/WHEEL
pysmtester-1.0.15.dist-info/entry_points.txt
pysmtester-1.0.15.dist-info/top_level.txt
pysmtester-1.0.15.dist-info/RECORD
