Metadata-Version: 2.1
Name: pysmtester
Version: 1.0.15
Summary: pysmtester
Home-page: http://www.sonmicro.com/
Author: SonMicro Electronics
Author-email: info@sonmicro.com
License: MIT
Requires-Dist: pyserial
